sopel_rulesof/__init__.py
sopel_rulesof/types.py
sopel_rulesof/util.py
sopel_rulesof/acquisition/__init__.py
sopel_rulesof/acquisition/plugin.py
sopel_rulesof/acquisition/types.py
sopel_rulesof/the_internet/__init__.py
sopel_rulesof/the_internet/plugin.py
sopel_rulesof/the_internet/types.py
sopel_rulesof-0.1.0.dist-info/COPYING
sopel_rulesof-0.1.0.dist-info/METADATA
sopel_rulesof-0.1.0.dist-info/WHEEL
sopel_rulesof-0.1.0.dist-info/entry_points.txt
sopel_rulesof-0.1.0.dist-info/top_level.txt
sopel_rulesof-0.1.0.dist-info/RECORD
